django_accounts_api/__init__.py
django_accounts_api/apps.py
django_accounts_api/forms/group.py
django_accounts_api/forms/user_create.py
django_accounts_api/migrations/__init__.py
django_accounts_api/templates/django_accounts_api/form.html
django_accounts_api/templates/django_accounts_api/password_reset_email.html
django_accounts_api/templates/django_accounts_api/password_reset_email_html.html
django_accounts_api/templates/django_accounts_api/password_reset_subject.txt
django_accounts_api/templates/django_accounts_api/schemas/group.json
django_accounts_api/templates/django_accounts_api/schemas/login.json
django_accounts_api/templates/django_accounts_api/schemas/user_update.json
django_accounts_api/templates/django_accounts_api/set_password_email.html
django_accounts_api/templates/django_accounts_api/set_password_email_html.html
django_accounts_api/templates/django_accounts_api/set_password_email_subject copy.txt
django_accounts_api/tests/groups/create_tests.py
django_accounts_api/tests/groups/delete_tests.py
django_accounts_api/tests/groups/list_tests.py
django_accounts_api/tests/groups/perms.py
django_accounts_api/tests/groups/update_tests.py
django_accounts_api/tests/login_tests.py
django_accounts_api/tests/manifest_tests.py
django_accounts_api/tests/membership/group_membership_tests.py
django_accounts_api/tests/membership/user_membership_tests.py
django_accounts_api/tests/password_change_tests.py
django_accounts_api/tests/password_reset_confirm_tests.py
django_accounts_api/tests/password_reset_tests.py
django_accounts_api/tests/permissions/filter_tests.py
django_accounts_api/tests/permissions/perms_group_create_tests.py
django_accounts_api/tests/permissions/perms_group_remove_tests.py
django_accounts_api/tests/permissions/perms_list_tests.py
django_accounts_api/tests/permissions/perms_user_create_tests.py
django_accounts_api/tests/permissions/perms_user_remove_tests.py
django_accounts_api/tests/users_tests.py
django_accounts_api/urls.py
django_accounts_api-1.2.5.dist-info/METADATA
django_accounts_api-1.2.5.dist-info/WHEEL
django_accounts_api-1.2.5.dist-info/RECORD
